inspect_flow/README.md
inspect_flow/__init__.py
inspect_flow/_version.py
inspect_flow/py.typed
inspect_flow/_api/__init__.py
inspect_flow/_api/api.py
inspect_flow/_cli/__init__.py
inspect_flow/_cli/config.py
inspect_flow/_cli/main.py
inspect_flow/_cli/options.py
inspect_flow/_cli/run.py
inspect_flow/_config/__init__.py
inspect_flow/_config/defaults.py
inspect_flow/_config/load.py
inspect_flow/_config/write.py
inspect_flow/_launcher/__init__.py
inspect_flow/_launcher/auto_dependencies.py
inspect_flow/_launcher/launch.py
inspect_flow/_launcher/pip_string.py
inspect_flow/_launcher/python_version.py
inspect_flow/_launcher/venv.py
inspect_flow/_runner/__init__.py
inspect_flow/_runner/instantiate.py
inspect_flow/_runner/resolve.py
inspect_flow/_runner/run.py
inspect_flow/_types/__init__.py
inspect_flow/_types/decorator.py
inspect_flow/_types/factories.py
inspect_flow/_types/flow_types.py
inspect_flow/_types/generated.py
inspect_flow/_types/merge.py
inspect_flow/_types/type_gen.py
inspect_flow/_util/__init__.py
inspect_flow/_util/args.py
inspect_flow/_util/constants.py
inspect_flow/_util/error.py
inspect_flow/_util/list_util.py
inspect_flow/_util/logging.py
inspect_flow/_util/module_util.py
inspect_flow/_util/not_given.py
inspect_flow/_util/path_util.py
inspect_flow/_util/subprocess_util.py
inspect_flow/api/__init__.py
inspect_flow-0.1.4.dist-info/METADATA
inspect_flow-0.1.4.dist-info/WHEEL
inspect_flow-0.1.4.dist-info/entry_points.txt
inspect_flow-0.1.4.dist-info/licenses/LICENSE
inspect_flow-0.1.4.dist-info/RECORD
