Metadata-Version: 2.4
Name: inspect_flow
Version: 0.1.4
Summary: Inspect Flow is a workflow stack built on Inspect AI that enables research organizations to run AI evaluations at scale
Project-URL: Source Code, https://github.com/meridianlabs-ai/inspect_flow
Project-URL: Issue Tracker, https://github.com/meridianlabs-ai/inspect_flow/issues
Project-URL: Documentation, https://meridianlabs-ai.github.io/inspect_flow/
Author: Meridian Labs
License: MIT License
License-File: LICENSE
Requires-Python: >=3.10
Requires-Dist: click>=8.2.1
Requires-Dist: inspect-ai>=0.3.147
Requires-Dist: packaging>=21.0
Requires-Dist: pydantic>=2.11.2
Requires-Dist: python-dotenv>=1.1.1
Requires-Dist: tomli>=2.0.0; python_version < '3.11'
Requires-Dist: typing-extensions>=4.9.0
Provides-Extra: doc
Requires-Dist: click; extra == 'doc'
Requires-Dist: griffe; extra == 'doc'
Requires-Dist: jupyter; extra == 'doc'
Requires-Dist: markdown; extra == 'doc'
Requires-Dist: panflute; extra == 'doc'
Requires-Dist: quarto-cli; extra == 'doc'
